hookbridge/__init__.py
hookbridge/client.py
hookbridge/errors.py
hookbridge/py.typed
hookbridge/types.py
hookbridge-1.0.0.dist-info/METADATA
hookbridge-1.0.0.dist-info/WHEEL
hookbridge-1.0.0.dist-info/RECORD
