Metadata-Version: 2.4
Name: hookbridge
Version: 1.0.0
Summary: Official HookBridge SDK for Python
Project-URL: Homepage, https://hookbridge.io
Project-URL: Documentation, https://hookbridge.io/docs/sdks/python
Project-URL: Repository, https://github.com/hookbridge/hookbridge-python
Project-URL: Issues, https://github.com/hookbridge/hookbridge-python/issues
Author-email: HookBridge <support@hookbridge.io>
License-Expression: MIT
Keywords: api,hookbridge,sdk,webhook,webhooks
Classifier: Development Status :: 5 - Production/Stable
Classifier: Intended Audience :: Developers
Classifier: License :: OSI Approved :: MIT License
Classifier: Operating System :: OS Independent
Classifier: Programming Language :: Python :: 3
Classifier: Programming Language :: Python :: 3.9
Classifier: Programming Language :: Python :: 3.10
Classifier: Programming Language :: Python :: 3.11
Classifier: Programming Language :: Python :: 3.12
Classifier: Programming Language :: Python :: 3.13
Classifier: Topic :: Internet :: WWW/HTTP
Classifier: Topic :: Software Development :: Libraries :: Python Modules
Classifier: Typing :: Typed
Requires-Python: >=3.9
Requires-Dist: httpx>=0.25.0
Provides-Extra: dev
Requires-Dist: mypy>=1.0; extra == 'dev'
Requires-Dist: pytest-asyncio>=0.21; extra == 'dev'
Requires-Dist: pytest-httpx>=0.21; extra == 'dev'
Requires-Dist: pytest>=7.0; extra == 'dev'
Requires-Dist: ruff>=0.1; extra == 'dev'
